[
  {
    "inputs": [
      {
        "internalType": "bytes32",
        "name": "table",
        "type": "bytes32"
      },
      {
        "internalType": "bytes32[]",
        "name": "key",
        "type": "bytes32[]"
      },
      {
        "internalType": "FieldLayout",
        "name": "fieldLayout",
        "type": "bytes32"
      }
    ],
    "name": "onAfterDeleteRecord",
    "outputs": [],
    "stateMutability": "nonpayable",
    "type": "function"
  },
  {
    "inputs": [
      {
        "internalType": "bytes32",
        "name": "table",
        "type": "bytes32"
      },
      {
        "internalType": "bytes32[]",
        "name": "key",
        "type": "bytes32[]"
      },
      {
        "internalType": "uint8",
        "name": "fieldIndex",
        "type": "uint8"
      },
      {
        "internalType": "bytes",
        "name": "data",
        "type": "bytes"
      },
      {
        "internalType": "FieldLayout",
        "name": "fieldLayout",
        "type": "bytes32"
      }
    ],
    "name": "onAfterSetField",
    "outputs": [],
    "stateMutability": "nonpayable",
    "type": "function"
  },
  {
    "inputs": [
      {
        "internalType": "bytes32",
        "name": "table",
        "type": "bytes32"
      },
      {
        "internalType": "bytes32[]",
        "name": "key",
        "type": "bytes32[]"
      },
      {
        "internalType": "bytes",
        "name": "staticData",
        "type": "bytes"
      },
      {
        "internalType": "PackedCounter",
        "name": "encodedLengths",
        "type": "bytes32"
      },
      {
        "internalType": "bytes",
        "name": "dynamicData",
        "type": "bytes"
      },
      {
        "internalType": "FieldLayout",
        "name": "fieldLayout",
        "type": "bytes32"
      }
    ],
    "name": "onAfterSetRecord",
    "outputs": [],
    "stateMutability": "nonpayable",
    "type": "function"
  },
  {
    "inputs": [
      {
        "internalType": "bytes32",
        "name": "table",
        "type": "bytes32"
      },
      {
        "internalType": "bytes32[]",
        "name": "key",
        "type": "bytes32[]"
      },
      {
        "internalType": "FieldLayout",
        "name": "fieldLayout",
        "type": "bytes32"
      }
    ],
    "name": "onBeforeDeleteRecord",
    "outputs": [],
    "stateMutability": "nonpayable",
    "type": "function"
  },
  {
    "inputs": [
      {
        "internalType": "bytes32",
        "name": "table",
        "type": "bytes32"
      },
      {
        "internalType": "bytes32[]",
        "name": "key",
        "type": "bytes32[]"
      },
      {
        "internalType": "uint8",
        "name": "fieldIndex",
        "type": "uint8"
      },
      {
        "internalType": "bytes",
        "name": "data",
        "type": "bytes"
      },
      {
        "internalType": "FieldLayout",
        "name": "fieldLayout",
        "type": "bytes32"
      }
    ],
    "name": "onBeforeSetField",
    "outputs": [],
    "stateMutability": "nonpayable",
    "type": "function"
  },
  {
    "inputs": [
      {
        "internalType": "bytes32",
        "name": "table",
        "type": "bytes32"
      },
      {
        "internalType": "bytes32[]",
        "name": "key",
        "type": "bytes32[]"
      },
      {
        "internalType": "bytes",
        "name": "staticData",
        "type": "bytes"
      },
      {
        "internalType": "PackedCounter",
        "name": "encodedLengths",
        "type": "bytes32"
      },
      {
        "internalType": "bytes",
        "name": "dynamicData",
        "type": "bytes"
      },
      {
        "internalType": "FieldLayout",
        "name": "fieldLayout",
        "type": "bytes32"
      }
    ],
    "name": "onBeforeSetRecord",
    "outputs": [],
    "stateMutability": "nonpayable",
    "type": "function"
  },
  {
    "inputs": [
      {
        "internalType": "bytes4",
        "name": "interfaceID",
        "type": "bytes4"
      }
    ],
    "name": "supportsInterface",
    "outputs": [
      {
        "internalType": "bool",
        "name": "",
        "type": "bool"
      }
    ],
    "stateMutability": "view",
    "type": "function"
  }
]